{
	"projects": [
		{
			"idx": 0,
			"name": "My Dotfiles",
			"gif-path": "https://res.cloudinary.com/practicaldev/image/fetch/s--2iCelOVj--/c_imagga_scale,f_auto,fl_progressive,h_900,q_auto,w_1600/https://dev-to-uploads.s3.amazonaws.com/i/17g34k8qfwhl0syrf30y.png",
			"description": "My personal configuration files for zsh, nvim & tmux.",
			"used-technologies": [
				"Shell (bash & zsh)",
				"Vim script",
				"Browsing configuration files"
			],
			"link-to-code": "https://github.com/buduboti/dotfiles",
			"link-to-demo": null
		},
		{
			"idx": 1,
			"name": "Zapp",
			"gif-path": "/project-pic/zapp.png",
			"description": "An asynchronous messaging app for businesses.",
			"used-technologies": [
				"Docker containers",
				"NodeJS",
				"AWS"
			],
			"link-to-code": null,
			"link-to-demo": "https://lets-zapp.com"
		},
		{
			"idx": 2,
			"name": "Mandelbrot fractal in x86 Assembly",
			"gif-path": "/project-pic/asm.gif",
			"description": "An optional university project.",
			"used-technologies": [
				"Complex mathematical calculations",
				"SSE optimalization",
				"Choose between single/double float precision",
				"Input handling"
			],
			"link-to-code": "https://github.com/buduboti/mandelbrot-assembly",
			"link-to-demo": null
		},
		{
			"idx": 3,
			"name": "Mor-C",
			"gif-path": "https://media.hswstatic.com/eyJidWNrZXQiOiJjb250ZW50Lmhzd3N0YXRpYy5jb20iLCJrZXkiOiJnaWZcL21vcnNlLWNvZGUuanBnIiwiZWRpdHMiOnsicmVzaXplIjp7IndpZHRoIjo4Mjh9fX0=",
			"description": "A compilator for our own programming language, highly inspired by the morse code.",
			"used-technologies": [
				"Bison",
				"Flex",
				"C"
			],
			"link-to-code": "https://gitlab.com/konczeizalan/form-lis",
			"link-to-demo": null
		},
		{
			"idx": 4,
			"name": "2048-AI",
			"gif-path": "/project-pic/2048.png",
			"description": "An A.I. who plays 2048.",
			"used-technologies": [
				"Monte Carlo tree search (MCTS)",
				"Python"
			],
			"link-to-code": "https://github.com/buduboti/2048-monte-carlo-AI",
			"link-to-demo": null
		}
	]
}
